marshmallow_pynamodb/__init__.py
marshmallow_pynamodb/convert.py
marshmallow_pynamodb/fields.py
marshmallow_pynamodb/schema.py
marshmallow_pynamo_db-1.1.0.dist-info/WHEEL
marshmallow_pynamo_db-1.1.0.dist-info/METADATA
marshmallow_pynamo_db-1.1.0.dist-info/RECORD
