Metadata-Version: 2.1
Name: marshmallow-pynamo-db
Version: 1.1.0
Summary: PynamoDB integration with the Marshmallow (de)serialization library
Home-page: https://github.com/chrismaille/marshmallow-pynamodb
License: MIT
Author: Mathew Marcus
Author-email: mathewmarcus456@gmail.com
Requires-Python: >=3.7,<4
Classifier: License :: OSI Approved :: MIT License
Classifier: Programming Language :: Python :: 3
Classifier: Programming Language :: Python :: 3.10
Classifier: Programming Language :: Python :: 3.7
Classifier: Programming Language :: Python :: 3.8
Classifier: Programming Language :: Python :: 3.9
Requires-Dist: marshmallow (>=3.0)
Requires-Dist: marshmallow_enum
Requires-Dist: pynamodb (>=5.0.0)
Project-URL: Repository, https://github.com/chrismaille/marshmallow-pynamodb
